skil_client/__init__.py
skil_client/api_client.py
skil_client/configuration.py
skil_client/exceptions.py
skil_client/rest.py
skil_client/api/__init__.py
skil_client/api/default_api.py
skil_client/models/__init__.py
skil_client/models/accumulated_results.py
skil_client/models/add_credentials_request.py
skil_client/models/add_example_request.py
skil_client/models/add_model_history_request.py
skil_client/models/add_resource_request.py
skil_client/models/aggregate_prediction.py
skil_client/models/auth_policy.py
skil_client/models/azure_storage_resource_details.py
skil_client/models/base64_nd_array_body.py
skil_client/models/base64_nd_array_body_knn.py
skil_client/models/batch_csv_record.py
skil_client/models/batch_record.py
skil_client/models/best_model.py
skil_client/models/change_password_request.py
skil_client/models/classification_result.py
skil_client/models/create_deployment_request.py
skil_client/models/create_job_request.py
skil_client/models/data_proc_resource_details.py
skil_client/models/deployment_objects.py
skil_client/models/deployment_response.py
skil_client/models/detected_object.py
skil_client/models/detection_result.py
skil_client/models/download_output_file_request.py
skil_client/models/emr_resource_details.py
skil_client/models/evaluation_results_entity.py
skil_client/models/example_entity.py
skil_client/models/experiment_entity.py
skil_client/models/feedback_response.py
skil_client/models/file_upload.py
skil_client/models/file_upload_list.py
skil_client/models/google_storage_resource_details.py
skil_client/models/hd_insight_resource_details.py
skil_client/models/hdfs_resource_details.py
skil_client/models/import_model_request.py
skil_client/models/ind_array.py
skil_client/models/inline_response200.py
skil_client/models/job_entity.py
skil_client/models/json_array_response.py
skil_client/models/log_batch.py
skil_client/models/log_request.py
skil_client/models/login_request.py
skil_client/models/login_response.py
skil_client/models/minibatch_entity.py
skil_client-1.2.2.0.dist-info/METADATA
skil_client-1.2.2.0.dist-info/WHEEL
skil_client-1.2.2.0.dist-info/top_level.txt
skil_client-1.2.2.0.dist-info/RECORD
